{
  "type": "minecraft:blasting",
  "ingredient": [
    {
      "item": "simple_metalcraft:copper_pickaxe"
    },
    {
      "item": "simple_metalcraft:copper_shovel"
    },
    {
      "item": "simple_metalcraft:copper_axe"
    },
    {
      "item": "simple_metalcraft:copper_hoe"
    },
    {
      "item": "simple_metalcraft:copper_sword"
    },
    {
      "item": "simple_metalcraft:copper_helmet"
    },
    {
      "item": "simple_metalcraft:copper_chestplate"
    },
    {
      "item": "simple_metalcraft:copper_leggings"
    },
    {
      "item": "simple_metalcraft:copper_boots"
    }
  ],
  "result": "simple_metalcraft:copper_nugget",
  "experience": 0.1,
  "cookingtime": 100
}